pyvoa_full/__init__.py
pyvoa_full-0.1.1.dist-info/LICENSE
pyvoa_full-0.1.1.dist-info/METADATA
pyvoa_full-0.1.1.dist-info/WHEEL
pyvoa_full-0.1.1.dist-info/top_level.txt
pyvoa_full-0.1.1.dist-info/RECORD
